itk/Configuration/ITKMetricsv4Config.py
itk/Configuration/ITKMetricsv4_snake_case.py
itk/Configuration/ITKOptimizersv4Config.py
itk/Configuration/ITKOptimizersv4_snake_case.py
itk/Configuration/ITKPDEDeformableRegistrationConfig.py
itk/Configuration/ITKPDEDeformableRegistration_snake_case.py
itk/Configuration/ITKRegistrationCommonConfig.py
itk/Configuration/ITKRegistrationCommon_snake_case.py
itk/Configuration/ITKRegistrationMethodsv4Config.py
itk/Configuration/ITKRegistrationMethodsv4_snake_case.py
itk/ITKMetricsv4Python.py
itk/ITKOptimizersv4Python.py
itk/ITKPDEDeformableRegistrationPython.py
itk/ITKRegistrationCommonPython.py
itk/ITKRegistrationMethodsv4Python.py
itk/_ITKMetricsv4Python.cpython-39-darwin.so
itk/_ITKOptimizersv4Python.cpython-39-darwin.so
itk/_ITKPDEDeformableRegistrationPython.cpython-39-darwin.so
itk/_ITKRegistrationCommonPython.cpython-39-darwin.so
itk/_ITKRegistrationMethodsv4Python.cpython-39-darwin.so
itk/itkANTSNeighborhoodCorrelationImageToImageMetricv4Python.py
itk/itkAmoebaOptimizerv4Python.py
itk/itkBSplineSyNImageRegistrationMethodPython.py
itk/itkBlockMatchingImageFilterPython.py
itk/itkCenteredTransformInitializerPython.py
itk/itkCenteredVersorTransformInitializerPython.py
itk/itkCommandIterationUpdatev4Python.py
itk/itkConjugateGradientLineSearchOptimizerv4Python.py
itk/itkCorrelationImageToImageMetricv4Python.py
itk/itkDemonsImageToImageMetricv4Python.py
itk/itkDemonsRegistrationFilterPython.py
itk/itkDiffeomorphicDemonsRegistrationFilterPython.py
itk/itkEuclideanDistancePointSetToPointSetMetricv4Python.py
itk/itkExhaustiveOptimizerv4Python.py
itk/itkExpectationBasedPointSetToPointSetMetricv4Python.py
itk/itkGradientDescentLineSearchOptimizerv4Python.py
itk/itkGradientDescentOptimizerBasev4Python.py
itk/itkGradientDescentOptimizerv4Python.py
itk/itkGradientDifferenceImageToImageMetricPython.py
itk/itkImageRegistrationMethodPython.py
itk/itkImageRegistrationMethodv4Python.py
itk/itkImageToImageMetricPython.py
itk_registration-5.4.4.post1.dist-info/METADATA
itk_registration-5.4.4.post1.dist-info/WHEEL
itk_registration-5.4.4.post1.dist-info/licenses/LICENSE
itk_registration-5.4.4.post1.dist-info/licenses/ITK-source/ITK/LICENSE
itk_registration-5.4.4.post1.dist-info/licenses/ITK-source/ITK/NOTICE
itk_registration-5.4.4.post1.dist-info/RECORD
